crypto_whitepapers_mcp/__init__.py
crypto_whitepapers_mcp/cli.py
crypto_whitepapers_mcp-0.1.0.dist-info/METADATA
crypto_whitepapers_mcp-0.1.0.dist-info/WHEEL
crypto_whitepapers_mcp-0.1.0.dist-info/entry_points.txt
crypto_whitepapers_mcp-0.1.0.dist-info/licenses/LICENSE
crypto_whitepapers_mcp-0.1.0.dist-info/RECORD
