Metadata-Version: 2.4
Name: crypto-whitepapers-mcp
Version: 0.1.0
Summary: An MCP server serving as a structured knowledge base of crypto whitepapers for AI agents to access, analyze, and learn from.
License-File: LICENSE
Requires-Python: >=3.10
Requires-Dist: agno>=1.3.4
Requires-Dist: duckduckgo-search>=8.0.1
Requires-Dist: fastembed>=0.6.1
Requires-Dist: lancedb>=0.21.2
Requires-Dist: mcp[cli]>=1.6.0
Requires-Dist: numpy>=2.2.4
Requires-Dist: pandas>=2.2.3
Requires-Dist: pypdf>=5.4.0
